fast_mathutils-0.1.0.dist-info/licenses/LICENSE
pymathutils/__init__.py
pymathutils/arithmetic.py
pymathutils/number_theory.py
fast_mathutils-0.1.0.dist-info/METADATA
fast_mathutils-0.1.0.dist-info/WHEEL
fast_mathutils-0.1.0.dist-info/top_level.txt
fast_mathutils-0.1.0.dist-info/RECORD
