Metadata-Version: 2.4
Name: fast-mathutils
Version: 0.1.0
Summary: Simple self-contained math utilities (factorial, Fibonacci, gcd, lcm, primes).
Author-email: Natee Junrungsee <33nateejunrungsee@lannaist.ac.th>
License: MIT
Project-URL: Homepage, https://github.com/SuperHappyCat/pymathutils
Classifier: Programming Language :: Python :: 3
Classifier: License :: OSI Approved :: MIT License
Classifier: Operating System :: OS Independent
Requires-Python: >=3.7
License-File: LICENSE
Dynamic: license-file
